bibat/__init__.py
bibat/fitting.py
bibat/fitting_mode.py
bibat/inference_configuration.py
bibat/prepared_data.py
bibat/util.py
bibat-0.3.4.dist-info/LICENSE
bibat-0.3.4.dist-info/METADATA
bibat-0.3.4.dist-info/WHEEL
bibat-0.3.4.dist-info/top_level.txt
bibat-0.3.4.dist-info/RECORD
