Metadata-Version: 2.1
Name: bibat
Version: 0.3.4
Summary: Batteries-included Bayesian analysis template
Author-email: Teddy Groves <tedgro@dtu.dk>
License: GNU General Public License version 3
Project-URL: homepage, https://github.com/teddygroves/bibat
Project-URL: download, https://pypi.org/project/bibat
Project-URL: documentation, https://bibat.readthedocs.io/
Classifier: Development Status :: 2 - Pre-Alpha
Classifier: Intended Audience :: Science/Research
Classifier: License :: OSI Approved :: GNU General Public License v3 (GPLv3)
Classifier: Natural Language :: English
Classifier: Operating System :: MacOS :: MacOS X
Classifier: Operating System :: Microsoft :: Windows :: Windows 10
Classifier: Operating System :: POSIX
Classifier: Topic :: Scientific/Engineering :: Information Analysis
Requires-Python: >=3.11
License-File: LICENSE
Requires-Dist: arviz
Requires-Dist: cmdstanpy
Requires-Dist: copier
Requires-Dist: numpy
Requires-Dist: pandas
Requires-Dist: pandera
Requires-Dist: pip >=20
Requires-Dist: pydantic
Requires-Dist: pyyaml-include <2
Requires-Dist: scikit-learn
Requires-Dist: scipy <1.13
Requires-Dist: stanio
Requires-Dist: toml
Requires-Dist: xarray
Requires-Dist: zarr
Provides-Extra: development
Requires-Dist: black ; extra == 'development'
Requires-Dist: pre-commit ; extra == 'development'
Requires-Dist: codecov ; extra == 'development'
Requires-Dist: mkdocs ; extra == 'development'
Requires-Dist: mkdocs-material ; extra == 'development'
Requires-Dist: mkdocstrings ; extra == 'development'
Requires-Dist: mkdocstrings-python ; extra == 'development'
Requires-Dist: pymdown-extensions ; extra == 'development'
Requires-Dist: pytest ; extra == 'development'
Requires-Dist: pytest-cov ; extra == 'development'
Requires-Dist: tox ; extra == 'development'
Requires-Dist: ruff ; extra == 'development'
